LICENSE
MANIFEST.in
README.md
requirements.txt
setup.py
hacker.egg-info/PKG-INFO
hacker.egg-info/SOURCES.txt
hacker.egg-info/dependency_links.txt
hacker.egg-info/requires.txt
hacker.egg-info/top_level.txt
hackernews/__init__.py
hackernews/settings.py
tests/__init__.py
tests/test_api_verison.py
tests/test_ask_stories.py
tests/test_get_item.py
tests/test_get_max_item.py
tests/test_get_user.py
tests/test_job_stories.py
tests/test_new_stories.py
tests/test_show_stories.py
tests/test_top_stories.py
tests/test_updates.py